locdata/__init__.py
locdata/activity.py
locdata/analytics.py
locdata/charts.py
locdata/custom_exception.py
locdata/logger.py
locdata/timer.py
locdata-0.0.4.dist-info/LICENSE
locdata-0.0.4.dist-info/METADATA
locdata-0.0.4.dist-info/WHEEL
locdata-0.0.4.dist-info/top_level.txt
locdata-0.0.4.dist-info/RECORD
